mad_services/__init__.py
mad_services/box.py
mad_services/data/min-igen.mdp
mad_services/data/rel-igen.mdp
mad_services/data/water.gro
mad_services/insane/builder/__init__.py
mad_services/insane/builder/luis.py
mad_services/insane/builder/utils.py
mad_services/loggers/mda.py
mad_services-1.0.3.dist-info/METADATA
mad_services-1.0.3.dist-info/WHEEL
mad_services-1.0.3.dist-info/entry_points.txt
mad_services-1.0.3.dist-info/RECORD
