Metadata-Version: 2.4
Name: mad-services
Version: 1.0.3
Summary: Add your description here
Author-email: glaunay <guillaume.launay@ens-lyon.fr>
Requires-Python: >=3.11
Requires-Dist: mdanalysis>=2.9.0
Requires-Dist: numpy>=2.3.1
Requires-Dist: rich-click>=1.9.4
